Metadata-Version: 1.0
Name: radico
Version: 0.0.1
Summary: Radiative transfer code
Home-page: https://github.com/astropenguin/radico
Author: astropenguin
Author-email: taniguchi@a.phys.nagoya-u.ac.jp
License: UNKNOWN
Platform: UNKNOWN
